CHANGELOG.rst
LICENSE
MANIFEST.in
README.rst
htttea.py
setup.py
htttea.egg-info/PKG-INFO
htttea.egg-info/SOURCES.txt
htttea.egg-info/dependency_links.txt
htttea.egg-info/requires.txt
htttea.egg-info/top_level.txt