Metadata-Version: 1.1
Name: htttea
Version: 0.0.1
Summary: Web server for testing.
Home-page: https://github.com/narusemotoki/htttea
Author: Motoki Naruse
Author-email: motoki@naru.se
License: MIT
Keywords: test,http
Platform: UNKNOWN
Classifier: Development Status :: 1 - Planning
Classifier: Intended Audience :: Developers
Classifier: License :: OSI Approved :: MIT License
Classifier: Programming Language :: Python :: 3
Classifier: Programming Language :: Python :: 3.6
Classifier: Programming Language :: Python :: 3 :: Only
Classifier: Topic :: Software Development :: Libraries
